custom_wkt-0.1.0.dist-info/METADATA
custom_wkt-0.1.0.dist-info/WHEEL
custom_wkt.pyd
custom_wkt-0.1.0.dist-info/RECORD
