Metadata-Version: 2.1
Name: custom-wkt
Version: 0.1.0
Requires-Dist: numpy>=1.16.0
Author: erik.langenborg@gmail.com
Author-Email: erik.langenborg@gmail.com
License: MIT
Requires-Python: >=3.6
